bimap/__init__.py
bimap/bimap.py
bimap-0.1.1.dist-info/METADATA
bimap-0.1.1.dist-info/RECORD
bimap-0.1.1.dist-info/WHEEL
bimap-0.1.1.dist-info/top_level.txt
